baluchon/__init__.py
baluchon/constants.py
baluchon/database.py
baluchon/exceptions.py
baluchon/manager.py
baluchon/migration.py
baluchon/source.py
baluchon/validator/__init__.py
baluchon/validator/schemas.py
baluchon-0.0.1.dist-info/WHEEL
baluchon-0.0.1.dist-info/METADATA
baluchon-0.0.1.dist-info/RECORD
